{
  "NameReport": "Мой отчет",
  "ID_Report": "1",
  "DataStore": "1",
  "ParametersList": [
{
      "id": "1",
      "name": "Дата начала",
      "type": "timestamp"
    },
{
      "id": "2",
      "name": "Дата конца",
      "type": "timestamp"
    },
{
      "id": "3",
      "name": "Limit",
      "type": "int"
    },
    {
      "id": "4",
      "name": "s_ip",
      "type": "query",
      "query": "SELECT s_ip FROM iislogi group by s_ip"
    }
  ],
  "SQL_Query": "U0VMRUNUICogRlJPTSBpaXNsb2dpIHdoZXJlICBcInRpbWVzdGFtcFwiIEJFVFdFRU4gJDEgYW5kICQyICBhbmQgc19pcCA9ICQ0IGxpbWl0ICQzOw=="
}